{"BookBlazorExample.States.ProductListState":[{"Name":"Products","Definition":"The products displayed in the list"},{"Name":"InStockOnly","Definition":"Whether the products in the list are filtered to show only those that are in stock"},{"Name":"FilterText","Definition":"Whether the products in the list are filtered to show only those whose names contains FilterText"}],"BookBlazorExample.States.ProductFormState":[{"Name":"Id","Definition":"The product\u0027s unique ID"},{"Name":"Name","Definition":"The product\u0027s name"},{"Name":"Price","Definition":"The product\u0027s price"},{"Name":"IsInStock","Definition":"Reflects whether the product is in stock"},{"Name":"CategoryId","Definition":"Identifies the product\u0027s category"},{"Name":"NameIsMissing","Definition":"Defines whether state.Name, which is required, is missing."},{"Name":"NameIsTooLong","Definition":"Defines whether state.Name is too long (100 chars max)."},{"Name":"NameIsInUse","Definition":"Defines whether state.Name, which must be unique, is already in use."},{"Name":"NameIsInvalid","Definition":"Defines whether state.Name is invalid. If it is invalid, InvalidNameErrorMessage has a value indicating why."},{"Name":"InvalidNameErrorMessage","Definition":"Defines the validation error message in case state.NameIsInvalid equals true."},{"Name":"PriceIsInvalid","Definition":"Defines whether state.Price is invalid. If it is invalid, InvalidPriceErrorMessage has a value indicating why."},{"Name":"InvalidPriceErrorMessage","Definition":"Defines the validation error message in case state.PriceIsInvalid equals true."},{"Name":"CategoryIsInvalid","Definition":"Defines whether state.CategoryId is invalid. If it is invalid, InvalidCategoryErrorMessage has a value indicating why."},{"Name":"InvalidCategoryErrorMessage","Definition":"Defines the validation error message in case state.CategoryIsInvalid equals true."},{"Name":"ProductIsInvalid","Definition":"Defines whether the product is invalid, i.e. whether any of its properties is invalid.\n            If it is invalid, submits are disabled and the ErrorSummary is displayed."},{"Name":"ExistingProductNames","Definition":"Existing product names (all not null and not empty)"},{"Name":"NameIsRequired","Definition":"Error message indicating that the product\u0027s name must be supplied."},{"Name":"NameHasMaxLength","Definition":"Error message indicating that the product\u0027s name\u0027s maximum length has been exceeded."},{"Name":"NameNotUnique","Definition":"Error message indicating that the product\u0027s name is not unque."},{"Name":"PriceRequired","Definition":"Error message indicating that the product\u0027s price must be supplied."},{"Name":"CategoryRequired","Definition":"Error message indicating that the product\u0027s category must be supplied."}]}